facex/__init__.py
facex/facex.py
facex/model_optimized.tflite
hfahrudin-0.0.7.dist-info/LICENSE
hfahrudin-0.0.7.dist-info/METADATA
hfahrudin-0.0.7.dist-info/WHEEL
hfahrudin-0.0.7.dist-info/top_level.txt
hfahrudin-0.0.7.dist-info/RECORD
