Metadata-Version: 2.1
Name: hfahrudin
Version: 0.0.7
Summary: Facial Expression Classifier API
Home-page: https://github.com/hfahrudin/facex
Author: Hasby Fahrudin
Author-email: fahrudinhasby12@gmail.com
License: UNKNOWN
Platform: UNKNOWN
Classifier: Programming Language :: Python :: 3
Classifier: License :: OSI Approved :: MIT License
Classifier: Operating System :: OS Independent
Requires-Python: >=3.6
Requires-Dist: scikit-image (>=0.16.2)
